processing/__init__.py
processing/combination.py
processing/transformation.py
utils/__init__.py
utils/io.py
utils/plot.py
packge_name-0.0.1.dist-info/METADATA
packge_name-0.0.1.dist-info/WHEEL
packge_name-0.0.1.dist-info/top_level.txt
packge_name-0.0.1.dist-info/RECORD
